loan/__init__.py
loan/loan.py
cash_balance-0.0.2.dist-info/METADATA
cash_balance-0.0.2.dist-info/WHEEL
cash_balance-0.0.2.dist-info/top_level.txt
cash_balance-0.0.2.dist-info/RECORD
